docs/__init__.py
docs/conf.py
srm/__init__.py
srm/measure.py
srmpy-0.1.0.dist-info/METADATA
srmpy-0.1.0.dist-info/WHEEL
srmpy-0.1.0.dist-info/top_level.txt
srmpy-0.1.0.dist-info/RECORD
