Metadata-Version: 2.1
Name: srmpy
Version: 0.1.0
Summary: A package for mathematical calculations
Home-page: https://github.com/ishaileshmishra/srmpy.git
Author: Shailesh Mishra
Author-email: mshaileshr@gmail.com
License: UNKNOWN
Platform: UNKNOWN
Classifier: License :: OSI Approved :: MIT License
Classifier: Operating System :: OS Independent
Classifier: Intended Audience :: Developers
Classifier: Natural Language :: English
Classifier: Programming Language :: Python :: 3.6
Classifier: Programming Language :: Python :: 3.7
Requires-Python: >=3.6
